<annotation>
	<folder>train</folder>
	<filename>fall_9_jpg.rf.1b5257b03d0e30dfeff7f27780108b11.jpg</filename>
	<path>C:\Users\elleBee\Downloads\train\fall_9_jpg.rf.1b5257b03d0e30dfeff7f27780108b11.jpg</path>
	<source>
		<database>Unknown</database>
	</source>
	<size>
		<width>2304</width>
		<height>1440</height>
		<depth>3</depth>
	</size>
	<segmented>0</segmented>
	<object>
		<name>fall</name>
		<pose>Unspecified</pose>
		<truncated>0</truncated>
		<difficult>0</difficult>
		<bndbox>
			<xmin>876</xmin>
			<ymin>509</ymin>
			<xmax>1269</xmax>
			<ymax>1051</ymax>
		</bndbox>
	</object>
</annotation>
