<annotation>
	<folder>train</folder>
	<filename>no_9_jpg.rf.207063dcdefd0a9c4c30d682c6bb5d9b.jpg</filename>
	<path>C:\Users\elleBee\Downloads\train\no_9_jpg.rf.207063dcdefd0a9c4c30d682c6bb5d9b.jpg</path>
	<source>
		<database>Unknown</database>
	</source>
	<size>
		<width>2304</width>
		<height>1440</height>
		<depth>3</depth>
	</size>
	<segmented>0</segmented>
	<object>
		<name>no</name>
		<pose>Unspecified</pose>
		<truncated>0</truncated>
		<difficult>0</difficult>
		<bndbox>
			<xmin>870</xmin>
			<ymin>969</ymin>
			<xmax>1547</xmax>
			<ymax>1273</ymax>
		</bndbox>
	</object>
</annotation>
